{
  "Users": [
    {
      "fullName": "Duc Hanu",
      "email": "admin@gmail.com",
      "address": "363 Service Alley",
      "birthday": "27/03/2001",
      "gender": "Male",
      "phone": "(786) 1554473",
      "id": 1,
      "password": "1234"
    },
    {
      "id": 2,
      "fullName": "Alvie Copozio",
      "email": "acopozio0@vk.com",
      "gender": "Male",
      "address": "363 Service Alley",
      "phone": "(786) 1554473",
      "birthday": "27/03/2001",
      "photo": ["htt"],
      "password": "123"
    },
    {
      "id": 3,
      "fullName": "Ramsey Rosberg",
      "email": "rrosberg1@ibm.com",
      "gender": "Male",
      "address": "6187 Burrows Center",
      "phone": "(715) 3116971",
      "birthday": "25/04/1996",
      "photo": ["htt"],
      "password": "123"
    },
    {
      "id": 4,
      "fullName": "Natala Eke",
      "email": "neke2@china.com.cn",
      "gender": "Female",
      "address": "1 Esker Point",
      "phone": "(113) 7442515",
      "birthday": "19/10/2002",
      "photo": ["htt"],
      "password": "123"
    },
    {
      "id": 5,
      "fullName": "Christabel Lindup",
      "email": "clindup3@taobao.com",
      "gender": "Female",
      "address": "2655 Roxbury Drive",
      "phone": "(311) 2451823",
      "birthday": "14/11/1991",
      "photo": ["htt"],
      "password": "123"
    },
    {
      "id": 6,
      "fullName": "Trueman Kollaschek",
      "email": "tkollaschek4@technorati.com",
      "gender": "Male",
      "address": "0086 Monterey Alley",
      "phone": "(833) 5019701",
      "birthday": "25/12/1995",
      "photo": ["htt"],
      "password": "123"
    }
  ],
  "Employees": [
    {
      "fullName": "Alvie Copozio ",
      "email": "acopozio0@vk.com",
      "gender": "Male",
      "address": "363 Service Alley",
      "phone": "(786) 1554473",
      "birthday": "27/03/2001",
      "photo": "http://dummyimage.com/176x196.png/dddddd/000000",
      "id": 2
    },
    {
      "id": 3,
      "fullName": "Ramsey Rosberg",
      "email": "rrosberg1@ibm.com",
      "gender": "Male",
      "address": "6187 Burrows Center",
      "phone": "(715) 3116971",
      "birthday": "25/04/1996",
      "photo": "http://dummyimage.com/176x196.png/dddddd/000000",
      "password": "123"
    },
    {
      "fullName": "Natala Eke",
      "email": "neke2@china.com.cn",
      "gender": "Female",
      "address": "1 Esker Point",
      "phone": "(113) 7442515",
      "birthday": "19/10/2002",
      "photo": "http://dummyimage.com/176x196.png/dddddd/000000",
      "id": 4
    },
    {
      "id": 5,
      "fullName": "Christabel Lindup",
      "email": "clindup3@taobao.com",
      "gender": "Female",
      "address": "2655 Roxbury Drive",
      "phone": "(311) 2451823",
      "birthday": "14/11/1991",
      "photo": "http://dummyimage.com/181x166.png/dddddd/000000",
      "password": "123"
    },
    {
      "fullName": "Trueman Kollaschek",
      "email": "tkollaschek4@technorati.com",
      "gender": "Male",
      "address": "0086 Monterey Alley",
      "phone": "(833) 5019701",
      "birthday": "25/12/1995",
      "photo": "http://dummyimage.com/186x184.png/cc0000/ffffff",
      "id": 6
    },
    {
      "fullName": "Trueman Kollaschek",
      "email": "tkollaschek4@technorati.com",
      "gender": "Nam",
      "address": "0086 Monterey Alley",
      "phone": "8335019701",
      "birthday": "19/10/2002",
      "photo": "http://dummyimage.com/176x196.png/dddddd/000000",
      "id": 7
    }
  ],
  "Customers": [
    {
      "id": 1,
      "fullName": "Reta Karolczyk",
      "email": "rkarolczyk0@umn.edu",
      "gender": "Female",
      "address": "812 Lindbergh Circle",
      "phone": "(952) 3640498",
      "birthday": "04/08/2002",
      "photo": ["htt"],
      "password": "123"
    },
    {
      "id": 1,
      "fullName": "Gertruda Plevey",
      "email": "gplevey1@springer.com",
      "gender": "Female",
      "address": "6066 Northwestern Trail",
      "phone": "(583) 2363250",
      "birthday": "29/05/1997",
      "photo": ["htt"],
      "password": "v8pPVL7HB1NK"
    },
    {
      "id": 2,
      "fullName": "Pate Bodle",
      "email": "pbodle2@imdb.com",
      "gender": "Male",
      "address": "02 Warner Court",
      "phone": "(898) 5216196",
      "birthday": "22/06/1994",
      "photo": ["htt"],
      "password": "9d2OUHJK"
    },
    {
      "id": 3,
      "fullName": "Javier Honnicott",
      "email": "jhonnicott3@booking.com",
      "gender": "Male",
      "address": "3 Eggendart Plaza",
      "phone": "(361) 7245297",
      "birthday": "22/12/1997",
      "photo": ["htt"],
      "password": "xOHD2SALUG6O"
    },
    {
      "id": 4,
      "fullName": "Athene Detloff",
      "email": "adetloff4@lulu.com",
      "gender": "Female",
      "address": "66798 Ilene Circle",
      "phone": "(901) 6764729",
      "birthday": "14/02/1994",
      "photo": ["htt"],
      "password": "lYEkJrui9N"
    },
    {
      "id": 5,
      "fullName": "Jarib Pendlebery",
      "email": "jpendlebery5@indiegogo.com",
      "gender": "Male",
      "address": "848 Amoth Circle",
      "phone": "(487) 4854813",
      "birthday": "20/01/2002",
      "photo": ["htt"],
      "password": "92tkKFb"
    },
    {
      "id": 6,
      "fullName": "Dulci Longforth",
      "email": "dlongforth6@technorati.com",
      "gender": "Female",
      "address": "395 Delladonna Circle",
      "phone": "(557) 3298700",
      "birthday": "31/07/2001",
      "photo": ["htt"],
      "password": "9iVhlpINZV0U"
    },
    {
      "id": 7,
      "fullName": "Myriam Annand",
      "email": "mannand7@latimes.com",
      "gender": "Female",
      "address": "425 Prairie Rose Plaza",
      "phone": "(203) 6106759",
      "birthday": "29/10/1997",
      "photo": ["htt"],
      "password": "NQdYfLRNVR1I"
    },
    {
      "id": 8,
      "fullName": "Zackariah Julian",
      "email": "zjulian8@lulu.com",
      "gender": "Male",
      "address": "004 Sachtjen Alley",
      "phone": "(421) 6974899",
      "birthday": "19/08/1992",
      "photo": ["htt"],
      "password": "w6xjGRlfAeV"
    },
    {
      "id": 9,
      "fullName": "Mariele Maccaig",
      "email": "mmaccaig9@nifty.com",
      "gender": "Female",
      "address": "538 Fuller Street",
      "phone": "(557) 5978383",
      "birthday": "10/03/1993",
      "photo": ["htt"],
      "password": "Orsyb1NFreq"
    },
    {
      "id": 10,
      "fullName": "Darcey Harborow",
      "email": "dharborowa@ca.gov",
      "gender": "Female",
      "address": "3415 Delaware Circle",
      "phone": "(682) 4541234",
      "birthday": "23/05/2004",
      "photo": ["htt"],
      "password": "T4Pa1Qe56eU8"
    },
    {
      "id": 11,
      "fullName": "Bourke Currington",
      "email": "bcurringtonb@histats.com",
      "gender": "Male",
      "address": "19 Elmside Avenue",
      "phone": "(136) 8614149",
      "birthday": "04/01/2001",
      "photo": ["htt"],
      "password": "rzimYcjNun"
    },
    {
      "id": 12,
      "fullName": "Cassi Duffill",
      "email": "cduffillc@cnn.com",
      "gender": "Female",
      "address": "29832 Artisan Hill",
      "phone": "(318) 3962649",
      "birthday": "11/04/2004",
      "photo": ["htt"],
      "password": "MJw9gt"
    },
    {
      "id": 13,
      "fullName": "Carmine Spaughton",
      "email": "cspaughtond@virginia.edu",
      "gender": "Male",
      "address": "003 3rd Pass",
      "phone": "(611) 1119008",
      "birthday": "12/03/1997",
      "photo": ["htt"],
      "password": "vM5VFo0LEU"
    },
    {
      "id": 14,
      "fullName": "Tamara Callum",
      "email": "tcallume@salon.com",
      "gender": "Female",
      "address": "8 Marquette Alley",
      "phone": "(536) 3776783",
      "birthday": "02/01/1996",
      "photo": ["htt"],
      "password": "ZPcM91Ru"
    }
  ],
  "Categories": [
    {
      "categoryName": "Áo Hoodie",
      "description": "Áo thu đông",
      "id": 1
    },
    {
      "id": 2,
      "categoryName": "Áo Vest và Balzer",
      "description": "Áo quý ông"
    },
    {
      "id": 3,
      "categoryName": "Áo Khoác",
      "description": "Áo thu đông"
    },
    {
      "id": 4,
      "categoryName": "Áo Ba lỗ",
      "description": "Áo mùa hè"
    },
    {
      "id": 5,
      "categoryName": "Quần Jean",
      "description": "Mang vào sẽ đẹp trai hơn"
    },
    {
      "id": 6,
      "categoryName": "Quần dài/Quần âu",
      "description": "Sự quý phái đang ở đây"
    },
    {
      "id": 7,
      "categoryName": "Quần Short",
      "description": "Quần làm tăng độ đẹp trai của bạn"
    }
  ],
  "Suppliers": [
    {
      "id": 2,
      "supplierName": "Cty THHH Quyền Anh",
      "contactName": "CTy TNHH Một Thành Viên DuCJDK",
      "address": "08997 Schiller Hill",
      "phone": "668-847-7905",
      "country": "VietNam",
      "city": "Qiaozi"
    },
    {
      "supplierName": "Cty THHH Thiện Đặng",
      "contactName": "CTy TNHH Một Thành Viên Thien101",
      "address": "3 Merchant Circle",
      "phone": "625-481-8722",
      "country": "VietNam",
      "city": "Khallat Şāliḩ",
      "id": 3
    },
    {
      "id": 4,
      "supplierName": "Cty THHH Trung Phan",
      "contactName": "CTy TNHH Một Thành Viên PCT",
      "address": "25903 Eggendart Lane",
      "phone": "734-113-4904",
      "country": "VietNam",
      "city": "Margasari"
    },
    {
      "id": 5,
      "supplierName": "Cty THHH Đức Trọng",
      "contactName": "CTy TNHH Một Thành Viên DuCJDK",
      "address": "38348 Esch Court",
      "phone": "926-203-1125",
      "country": "VietNam",
      "city": "Cancela"
    },
    {
      "supplierName": "Hạnh đẹp trai",
      "contactName": "CTy TNHH Một Thành Viên DuCJDK",
      "address": "38348 Esch Court",
      "phone": "5464094692",
      "country": "VietNam",
      "city": "Cancela",
      "id": 6
    }
  ],
  "Countries": [
    {
      "id": 1,
      "countryName": "Mexico"
    },
    {
      "id": 2,
      "countryName": "Kazakhstan"
    },
    {
      "id": 3,
      "countryName": "Portugal"
    },
    {
      "id": 4,
      "countryName": "Japan"
    },
    {
      "id": 5,
      "countryName": "Indonesia"
    },
    {
      "id": 6,
      "countryName": "Mozambique"
    },
    {
      "id": 7,
      "countryName": "United States"
    },
    {
      "id": 8,
      "countryName": "Slovenia"
    },
    {
      "id": 9,
      "countryName": "Czech Republic"
    },
    {
      "id": 10,
      "countryName": "Brunei"
    },
    {
      "id": 11,
      "countryName": "Switzerland"
    },
    {
      "id": 12,
      "countryName": "Portugal"
    },
    {
      "id": 13,
      "countryName": "China"
    },
    {
      "id": 14,
      "countryName": "Russia"
    },
    {
      "id": 15,
      "countryName": "Mexico"
    },
    {
      "id": 16,
      "countryName": "Japan"
    },
    {
      "id": 17,
      "countryName": "Iran"
    },
    {
      "id": 18,
      "countryName": "Indonesia"
    },
    {
      "id": 19,
      "countryName": "Uzbekistan"
    },
    {
      "id": 20,
      "countryName": "Russia"
    },
    {
      "id": 21,
      "countryName": "China"
    },
    {
      "id": 22,
      "countryName": "Philippines"
    },
    {
      "id": 23,
      "countryName": "China"
    },
    {
      "id": 24,
      "countryName": "China"
    },
    {
      "id": 25,
      "countryName": "Portugal"
    },
    {
      "id": 26,
      "countryName": "China"
    },
    {
      "id": 27,
      "countryName": "Tanzania"
    },
    {
      "id": 28,
      "countryName": "Aland Islands"
    },
    {
      "id": 29,
      "countryName": "Ukraine"
    },
    {
      "id": 30,
      "countryName": "Madagascar"
    },
    {
      "id": 31,
      "countryName": "Brazil"
    },
    {
      "id": 32,
      "countryName": "Indonesia"
    },
    {
      "id": 33,
      "countryName": "China"
    },
    {
      "id": 34,
      "countryName": "China"
    },
    {
      "id": 35,
      "countryName": "China"
    },
    {
      "id": 36,
      "countryName": "Portugal"
    },
    {
      "id": 37,
      "countryName": "China"
    },
    {
      "id": 38,
      "countryName": "Indonesia"
    },
    {
      "id": 39,
      "countryName": "Nigeria"
    },
    {
      "id": 40,
      "countryName": "Portugal"
    },
    {
      "id": 41,
      "countryName": "Ecuador"
    },
    {
      "id": 42,
      "countryName": "Czech Republic"
    },
    {
      "id": 43,
      "countryName": "Greece"
    },
    {
      "id": 44,
      "countryName": "Greece"
    },
    {
      "id": 45,
      "countryName": "Brazil"
    },
    {
      "id": 46,
      "countryName": "Russia"
    },
    {
      "id": 47,
      "countryName": "Portugal"
    },
    {
      "id": 48,
      "countryName": "Chile"
    },
    {
      "id": 49,
      "countryName": "Indonesia"
    },
    {
      "id": 50,
      "countryName": "Yemen"
    },
    {
      "id": 51,
      "countryName": "Syria"
    },
    {
      "id": 52,
      "countryName": "China"
    },
    {
      "id": 53,
      "countryName": "China"
    },
    {
      "id": 54,
      "countryName": "Ukraine"
    },
    {
      "id": 55,
      "countryName": "South Africa"
    },
    {
      "id": 56,
      "countryName": "China"
    },
    {
      "id": 57,
      "countryName": "Poland"
    },
    {
      "id": 58,
      "countryName": "Portugal"
    },
    {
      "id": 59,
      "countryName": "China"
    },
    {
      "id": 60,
      "countryName": "Czech Republic"
    },
    {
      "id": 61,
      "countryName": "France"
    },
    {
      "id": 62,
      "countryName": "Thailand"
    },
    {
      "id": 63,
      "countryName": "China"
    },
    {
      "id": 64,
      "countryName": "Albania"
    },
    {
      "id": 65,
      "countryName": "Indonesia"
    },
    {
      "id": 66,
      "countryName": "Russia"
    },
    {
      "id": 67,
      "countryName": "Republic of the Congo"
    },
    {
      "id": 68,
      "countryName": "Norway"
    },
    {
      "id": 69,
      "countryName": "Estonia"
    },
    {
      "id": 70,
      "countryName": "Costa Rica"
    },
    {
      "id": 71,
      "countryName": "Sweden"
    },
    {
      "id": 72,
      "countryName": "Syria"
    },
    {
      "id": 73,
      "countryName": "China"
    },
    {
      "id": 74,
      "countryName": "Indonesia"
    },
    {
      "id": 75,
      "countryName": "Colombia"
    },
    {
      "id": 76,
      "countryName": "China"
    },
    {
      "id": 77,
      "countryName": "China"
    },
    {
      "id": 78,
      "countryName": "United States"
    },
    {
      "id": 79,
      "countryName": "Ireland"
    },
    {
      "id": 80,
      "countryName": "Indonesia"
    },
    {
      "id": 81,
      "countryName": "Ukraine"
    },
    {
      "id": 82,
      "countryName": "Spain"
    },
    {
      "id": 83,
      "countryName": "Spain"
    },
    {
      "id": 84,
      "countryName": "VietNam"
    },
    {
      "id": 85,
      "countryName": "Niger"
    },
    {
      "id": 86,
      "countryName": "Kazakhstan"
    },
    {
      "id": 87,
      "countryName": "Thailand"
    },
    {
      "id": 88,
      "countryName": "Russia"
    },
    {
      "id": 89,
      "countryName": "Indonesia"
    },
    {
      "id": 90,
      "countryName": "France"
    },
    {
      "id": 91,
      "countryName": "Kenya"
    },
    {
      "id": 92,
      "countryName": "Japan"
    },
    {
      "id": 93,
      "countryName": "Hungary"
    },
    {
      "id": 94,
      "countryName": "Brazil"
    },
    {
      "id": 95,
      "countryName": "Panama"
    },
    {
      "id": 96,
      "countryName": "Syria"
    },
    {
      "id": 97,
      "countryName": "Malaysia"
    },
    {
      "id": 98,
      "countryName": "United States"
    },
    {
      "id": 99,
      "countryName": "Brazil"
    },
    {
      "id": 100,
      "countryName": "Philippines"
    }
  ],
  "Products": [
    {
      "id": 2,
      "productName": "Ao vest basic",
      "price": 3000,
      "CategoryId": 2,
      "SupplierId": 3,
      "unit": "Dollar",
      "photo": ["htt"],
      "size": ["M", "L", "XL"],
      "color": ["Đỏ", "Đen", "Trắng"],
      "quantity": 11
    },
    {
      "id": 4,
      "productName": "Ao thun thu đông",
      "price": 6000,
      "CategoryId": 4,
      "SupplierId": 5,
      "unit": "million",
      "photo": [""],
      "size": ["M", "L", "XL"],
      "color": ["Đỏ", "Đen", "Trắng"],
      "quantity": 13
    },
    {
      "id": 5,
      "productName": "Quần Jean ống rộng",
      "price": 5000,
      "CategoryId": 6,
      "SupplierId": 3,
      "unit": "million",
      "photo": [""],
      "size": ["M", "L", "XL"],
      "color": ["Đỏ", "Đen", "Trắng"],
      "quantity": 12
    }
  ],
  "Orders": [
    {
      "id": 1,
      "orderList": [
        {
          "ProductId": 1,
          "quantity": 1,
          "salePrice": 120000
        },
        {
          "ProductId": 2,
          "quantity": 2,
          "salePrice": 11000
        }
      ],
      "EmployeeID": 1,
      "CustomerID": 1,
      "orderTime": "12/1/2022",
      "finishedTime": "12/1/2022",
      "status": 1
    },
    {
      "id": 2,
      "orderList": [
        {
          "ProductId": 1,
          "quantity": 1,
          "salePrice": 120000
        },
        {
          "ProductId": 2,
          "quantity": 2,
          "salePrice": 11000
        }
      ],
      "EmployeeId": 3,
      "CustomerId": 1,
      "orderTime": "12/1/2022",
      "finishedTime": "12/1/2022",
      "status": 1
    },
    {
      "id": 3,
      "orderList": [
        {
          "ProductId": 1,
          "quantity": 1,
          "salePrice": 120000
        },
        {
          "ProductId": 2,
          "quantity": 2,
          "salePrice": 11000
        }
      ],
      "EmployeeId": 1,
      "CustomerId": 1,
      "orderTime": "12/1/2022",
      "finishedTime": "12/1/2022",
      "status": 1
    }
  ]
}
